lthash/__init__.py
lthash/core.py
lthash/lthash.py
lthash-0.1.0.dist-info/LICENSE
lthash-0.1.0.dist-info/METADATA
lthash-0.1.0.dist-info/WHEEL
lthash-0.1.0.dist-info/top_level.txt
lthash-0.1.0.dist-info/RECORD
