Metadata-Version: 2.1
Name: lthash
Version: 0.1.0
Summary: A lightweight homomorphic, commutative hash implementation
Home-page: https://github.com/JackEshkenazi/lthash
Author: Jack Eshkenazi
Author-email: noreply@example.com
Classifier: Programming Language :: Python :: 3
Classifier: License :: OSI Approved :: MIT License
Classifier: Operating System :: OS Independent
Requires-Python: >=3.6
License-File: LICENSE
